contracting/.gitignore
contracting/.version
contracting/__init__.py
contracting/client.py
contracting/config.py
contracting/compilation/__init__.py
contracting/compilation/compiler.py
contracting/compilation/linter.py
contracting/compilation/parser.py
contracting/compilation/whitelists.py
contracting/contracts/__init__.py
contracting/contracts/submission.s.py
contracting/db/__init__.py
contracting/db/contract.py
contracting/db/driver.py
contracting/db/encoder.py
contracting/db/orm.py
contracting/execution/__init__.py
contracting/execution/executor.py
contracting/execution/module.py
contracting/execution/runtime.py
contracting/execution/metering/__init__.py
contracting/execution/metering/cu_costs.const
contracting/execution/metering/tracer.c
contracting/execution/metering/tracer.cpython-36m-darwin.so
contracting/stdlib/__init__.py
contracting/stdlib/env.py
contracting/stdlib/bridge/__init__.py
contracting/stdlib/bridge/access.py
contracting/stdlib/bridge/decimal.py
contracting/stdlib/bridge/hashing.py
contracting/stdlib/bridge/imports.py
contracting/stdlib/bridge/orm.py
contracting/stdlib/bridge/random.py
contracting/stdlib/bridge/time.py
tests/__init__.py
tests/run.py
tests/utils.py
tests/final_gov/__init__.py
tests/final_gov/test_add_members.py
tests/final_gov/test_foundation.py
tests/final_gov/test_members.py
tests/final_gov/test_rewards.py
tests/final_gov/test_stamps.py
tests/final_gov/contracts/currency.s.py
tests/final_gov/contracts/elect_members.s.py
tests/final_gov/contracts/election_house.s.py
tests/final_gov/contracts/foundation.s.py
tests/final_gov/contracts/members.s.py
tests/final_gov/contracts/rewards.s.py
tests/final_gov/contracts/stamp_cost.s.py
tests/governance/__init__.py
tests/governance/test_election_house.py
tests/governance/test_even_simpler_election_house.py
tests/governance/test_foundation.py
tests/governance/test_master_candidates.py
tests/governance/test_masternodes.py
tests/governance/test_more_flexible_election_house.py
contracting-1.0.5.2.dist-info/LICENSE
contracting-1.0.5.2.dist-info/METADATA
contracting-1.0.5.2.dist-info/WHEEL
contracting-1.0.5.2.dist-info/top_level.txt
contracting-1.0.5.2.dist-info/zip-safe
contracting-1.0.5.2.dist-info/RECORD
