Metadata-Version: 2.1
Name: contracting
Version: 1.0.5.2
Summary: Python-based smart contract language and interpreter.
Home-page: https://github.com/Lamden/contracting
Author: Lamden
Author-email: team@lamden.io
License: UNKNOWN
Platform: UNKNOWN
Classifier: Programming Language :: Python :: 3.6
Requires-Dist: astor
Requires-Dist: pymongo
Requires-Dist: autopep8
Requires-Dist: stdlib-list
